world_rowing/__init__.py
world_rowing/__main__.py
world_rowing/api.py
world_rowing/cli.py
world_rowing/dashboard.py
world_rowing/livetracker.py
world_rowing/predict.py
world_rowing/races.py
world_rowing/utils.py
world_rowing/data/cov_pace.csv.gz
world_rowing/data/iso_country.json
world_rowing/data/mean_pace.csv.gz
world_rowing/data/flags/AC.png
world_rowing/data/flags/AD.png
world_rowing/data/flags/AE.png
world_rowing/data/flags/AF.png
world_rowing/data/flags/AG.png
world_rowing/data/flags/AI.png
world_rowing/data/flags/AL.png
world_rowing/data/flags/AM.png
world_rowing/data/flags/AO.png
world_rowing/data/flags/AQ.png
world_rowing/data/flags/AR.png
world_rowing/data/flags/AS.png
world_rowing/data/flags/AT.png
world_rowing/data/flags/AU.png
world_rowing/data/flags/AW.png
world_rowing/data/flags/AX.png
world_rowing/data/flags/AZ.png
world_rowing/data/flags/BA.png
world_rowing/data/flags/BB.png
world_rowing/data/flags/BD.png
world_rowing/data/flags/BE.png
world_rowing/data/flags/BF.png
world_rowing/data/flags/BG.png
world_rowing/data/flags/BH.png
world_rowing/data/flags/BI.png
world_rowing/data/flags/BJ.png
world_rowing/data/flags/BL.png
world_rowing/data/flags/BM.png
world_rowing/data/flags/BN.png
world_rowing/data/flags/BO.png
world_rowing/data/flags/BQ.png
world_rowing/data/flags/BR.png
world_rowing/data/flags/BS.png
world_rowing/data/flags/BT.png
world_rowing/data/flags/BV.png
world_rowing/data/flags/BW.png
world_rowing/data/flags/BY.png
world_rowing/data/flags/BZ.png
world_rowing/data/flags/CA-AB.png
world_rowing/data/flags/CA-BC.png
world_rowing/data/flags/CA-MB.png
world_rowing/data/flags/CA-NB.png
world_rowing/data/flags/CA-NL.png
world_rowing/data/flags/CA-NS.png
world_rowing/data/flags/CA-NT.png
world_rowing/data/flags/CA-NU.png
world_rowing/data/flags/CA-ON.png
world_rowing/data/flags/CA-PE.png
world_rowing/data/flags/CA-QC.png
world_rowing/data/flags/CA-SK.png
world_rowing/data/flags/CA-YT.png
world_rowing/data/flags/CA.png
world_rowing/data/flags/CC.png
world_rowing-0.1.15.dist-info/LICENSE
world_rowing-0.1.15.dist-info/METADATA
world_rowing-0.1.15.dist-info/WHEEL
world_rowing-0.1.15.dist-info/entry_points.txt
world_rowing-0.1.15.dist-info/top_level.txt
world_rowing-0.1.15.dist-info/RECORD
